{
    "mappings": {
        "Person": {
            "_meta": {
                "aet_parent_field": "household_id"
            },
            "_parent": {
                "type": "Household"
            }
        },
        "Building": {
            "_meta": {
                "aet_geopoint": "location",
                "aet_parent_field": "survey_id"
            },
            "properties": {
                "location": {
                    "type": "geo_point"
                }
            },
            "_parent": {
                "type": "Survey"
            }
        },
        "Household": {
            "_meta": {
                "aet_parent_field": "location_id"
            },
            "_parent": {
                "type": "Building"

            }
        },
        "Survey": {}
    }
}
